{"config":{"output_file":null,"full_docs":false,"pub_only":false,"reachable_only":false,"distro_crate":false,"signatures":false,"borrow_data":false},"version":"0.19.1","compilation":{"directory":"e:\\programming\\RustProjects\\rust_book_conspect\\lesson_5\\structures_5_3_syntacsis_method","program":"C:\\Users\\Inshallah\\.rustup\\toolchains\\stable-x86_64-pc-windows-msvc\\bin\\rls.exe","arguments":[],"output":"e:\\programming\\RustProjects\\rust_book_conspect\\lesson_5\\structures_5_3_syntacsis_method\\target\\rls\\debug\\deps\\libstructures_5_3_syntacsis_method-a626c57efaf3d08b.rmeta"},"prelude":{"crate_id":{"name":"structures_5_3_syntacsis_method","disambiguator":[8641122348896219607,0]},"crate_root":"src","external_crates":[{"file_name":"e:\\programming\\RustProjects\\rust_book_conspect\\lesson_5\\structures_5_3_syntacsis_method\\src\\main.rs","num":1,"id":{"name":"std","disambiguator":[8526938853280630398,0]}},{"file_name":"e:\\programming\\RustProjects\\rust_book_conspect\\lesson_5\\structures_5_3_syntacsis_method\\src\\main.rs","num":2,"id":{"name":"core","disambiguator":[5339428516588690145,0]}},{"file_name":"e:\\programming\\RustProjects\\rust_book_conspect\\lesson_5\\structures_5_3_syntacsis_method\\src\\main.rs","num":3,"id":{"name":"compiler_builtins","disambiguator":[263601903543822771,0]}},{"file_name":"e:\\programming\\RustProjects\\rust_book_conspect\\lesson_5\\structures_5_3_syntacsis_method\\src\\main.rs","num":4,"id":{"name":"rustc_std_workspace_core","disambiguator":[7343628043363739070,0]}},{"file_name":"e:\\programming\\RustProjects\\rust_book_conspect\\lesson_5\\structures_5_3_syntacsis_method\\src\\main.rs","num":5,"id":{"name":"alloc","disambiguator":[14796848713614703829,0]}},{"file_name":"e:\\programming\\RustProjects\\rust_book_conspect\\lesson_5\\structures_5_3_syntacsis_method\\src\\main.rs","num":6,"id":{"name":"libc","disambiguator":[2248661955232720858,0]}},{"file_name":"e:\\programming\\RustProjects\\rust_book_conspect\\lesson_5\\structures_5_3_syntacsis_method\\src\\main.rs","num":7,"id":{"name":"unwind","disambiguator":[6100837883140397065,0]}},{"file_name":"e:\\programming\\RustProjects\\rust_book_conspect\\lesson_5\\structures_5_3_syntacsis_method\\src\\main.rs","num":8,"id":{"name":"cfg_if","disambiguator":[6763488366047601591,0]}},{"file_name":"e:\\programming\\RustProjects\\rust_book_conspect\\lesson_5\\structures_5_3_syntacsis_method\\src\\main.rs","num":9,"id":{"name":"miniz_oxide","disambiguator":[79841370634592438,0]}},{"file_name":"e:\\programming\\RustProjects\\rust_book_conspect\\lesson_5\\structures_5_3_syntacsis_method\\src\\main.rs","num":10,"id":{"name":"rustc_std_workspace_alloc","disambiguator":[14720684392801985393,0]}},{"file_name":"e:\\programming\\RustProjects\\rust_book_conspect\\lesson_5\\structures_5_3_syntacsis_method\\src\\main.rs","num":11,"id":{"name":"adler","disambiguator":[1205045013435031913,0]}},{"file_name":"e:\\programming\\RustProjects\\rust_book_conspect\\lesson_5\\structures_5_3_syntacsis_method\\src\\main.rs","num":12,"id":{"name":"hashbrown","disambiguator":[9970316023349964410,0]}},{"file_name":"e:\\programming\\RustProjects\\rust_book_conspect\\lesson_5\\structures_5_3_syntacsis_method\\src\\main.rs","num":13,"id":{"name":"std_detect","disambiguator":[17496692589544781456,0]}},{"file_name":"e:\\programming\\RustProjects\\rust_book_conspect\\lesson_5\\structures_5_3_syntacsis_method\\src\\main.rs","num":14,"id":{"name":"rustc_demangle","disambiguator":[17700294896468204783,0]}},{"file_name":"e:\\programming\\RustProjects\\rust_book_conspect\\lesson_5\\structures_5_3_syntacsis_method\\src\\main.rs","num":15,"id":{"name":"panic_unwind","disambiguator":[8939469696884238691,0]}},{"file_name":"e:\\programming\\RustProjects\\rust_book_conspect\\lesson_5\\structures_5_3_syntacsis_method\\src\\main.rs","num":16,"id":{"name":"test","disambiguator":[7237187576116786995,0]}},{"file_name":"e:\\programming\\RustProjects\\rust_book_conspect\\lesson_5\\structures_5_3_syntacsis_method\\src\\main.rs","num":17,"id":{"name":"getopts","disambiguator":[7036629304586090026,0]}},{"file_name":"e:\\programming\\RustProjects\\rust_book_conspect\\lesson_5\\structures_5_3_syntacsis_method\\src\\main.rs","num":18,"id":{"name":"rustc_std_workspace_std","disambiguator":[9920224266467441956,0]}},{"file_name":"e:\\programming\\RustProjects\\rust_book_conspect\\lesson_5\\structures_5_3_syntacsis_method\\src\\main.rs","num":19,"id":{"name":"unicode_width","disambiguator":[4477600868815660682,0]}}],"span":{"file_name":"src\\main.rs","byte_start":921,"byte_end":9320,"line_start":11,"line_end":137,"column_start":1,"column_end":2}},"imports":[],"defs":[{"kind":"Mod","id":{"krate":0,"index":0},"span":{"file_name":"src\\main.rs","byte_start":921,"byte_end":9320,"line_start":11,"line_end":137,"column_start":1,"column_end":2},"name":"","qualname":"::","value":"src\\main.rs","parent":null,"children":[{"krate":0,"index":1},{"krate":0,"index":2},{"krate":0,"index":10},{"krate":0,"index":13},{"krate":0,"index":3},{"krate":0,"index":7},{"krate":0,"index":9},{"krate":0,"index":15}],"decl_id":null,"docs":"","sig":null,"attributes":[]},{"kind":"Struct","id":{"krate":0,"index":10},"span":{"file_name":"src\\main.rs","byte_start":945,"byte_end":954,"line_start":12,"line_end":12,"column_start":8,"column_end":17},"name":"Rectangle","qualname":"::Rectangle","value":"Rectangle { width, height }","parent":null,"children":[{"krate":0,"index":11},{"krate":0,"index":12}],"decl_id":null,"docs":"","sig":null,"attributes":[]},{"kind":"Field","id":{"krate":0,"index":11},"span":{"file_name":"src\\main.rs","byte_start":961,"byte_end":966,"line_start":13,"line_end":13,"column_start":5,"column_end":10},"name":"width","qualname":"::Rectangle::width","value":"u32","parent":{"krate":0,"index":10},"children":[],"decl_id":null,"docs":"","sig":null,"attributes":[]},{"kind":"Field","id":{"krate":0,"index":12},"span":{"file_name":"src\\main.rs","byte_start":977,"byte_end":983,"line_start":14,"line_end":14,"column_start":5,"column_end":11},"name":"height","qualname":"::Rectangle::height","value":"u32","parent":{"krate":0,"index":10},"children":[],"decl_id":null,"docs":"","sig":null,"attributes":[]},{"kind":"Local","id":{"krate":0,"index":1073741828},"span":{"file_name":"src\\main.rs","byte_start":1023,"byte_end":1027,"line_start":18,"line_end":18,"column_start":14,"column_end":18},"name":"self","qualname":"<Rectangle>::area::self","value":"&Rectangle","parent":null,"children":[],"decl_id":null,"docs":"","sig":null,"attributes":[]},{"kind":"Method","id":{"krate":0,"index":4},"span":{"file_name":"src\\main.rs","byte_start":1017,"byte_end":1021,"line_start":18,"line_end":18,"column_start":8,"column_end":12},"name":"area","qualname":"<Rectangle>::area","value":"fn area(&Self) -> u32","parent":null,"children":[],"decl_id":null,"docs":"","sig":null,"attributes":[]},{"kind":"Local","id":{"krate":0,"index":1073741829},"span":{"file_name":"src\\main.rs","byte_start":1092,"byte_end":1096,"line_start":22,"line_end":22,"column_start":15,"column_end":19},"name":"self","qualname":"<Rectangle>::width::self","value":"&Rectangle","parent":null,"children":[],"decl_id":null,"docs":"","sig":null,"attributes":[]},{"kind":"Method","id":{"krate":0,"index":5},"span":{"file_name":"src\\main.rs","byte_start":1085,"byte_end":1090,"line_start":22,"line_end":22,"column_start":8,"column_end":13},"name":"width","qualname":"<Rectangle>::width","value":"fn width(&Self) -> bool","parent":null,"children":[],"decl_id":null,"docs":"","sig":null,"attributes":[]},{"kind":"Local","id":{"krate":0,"index":1073741830},"span":{"file_name":"src\\main.rs","byte_start":2033,"byte_end":2037,"line_start":33,"line_end":33,"column_start":15,"column_end":19},"name":"size","qualname":"<Rectangle>::square::size","value":"u32","parent":null,"children":[],"decl_id":null,"docs":"","sig":null,"attributes":[]},{"kind":"Method","id":{"krate":0,"index":6},"span":{"file_name":"src\\main.rs","byte_start":2026,"byte_end":2032,"line_start":33,"line_end":33,"column_start":8,"column_end":14},"name":"square","qualname":"<Rectangle>::square","value":"fn square(u32) -> Self","parent":null,"children":[],"decl_id":null,"docs":"","sig":null,"attributes":[]},{"kind":"Local","id":{"krate":0,"index":1073741832},"span":{"file_name":"src\\main.rs","byte_start":2172,"byte_end":2176,"line_start":42,"line_end":42,"column_start":18,"column_end":22},"name":"self","qualname":"<Rectangle>::can_hold::self","value":"&Rectangle","parent":null,"children":[],"decl_id":null,"docs":"","sig":null,"attributes":[]},{"kind":"Local","id":{"krate":0,"index":536870920},"span":{"file_name":"src\\main.rs","byte_start":2178,"byte_end":2183,"line_start":42,"line_end":42,"column_start":24,"column_end":29},"name":"other","qualname":"<Rectangle>::can_hold::other","value":"&Rectangle","parent":null,"children":[],"decl_id":null,"docs":"","sig":null,"attributes":[]},{"kind":"Method","id":{"krate":0,"index":8},"span":{"file_name":"src\\main.rs","byte_start":2162,"byte_end":2170,"line_start":42,"line_end":42,"column_start":8,"column_end":16},"name":"can_hold","qualname":"<Rectangle>::can_hold","value":"fn can_hold(&Self, &Rectangle) -> bool","parent":null,"children":[],"decl_id":null,"docs":"","sig":null,"attributes":[]},{"kind":"Function","id":{"krate":0,"index":9},"span":{"file_name":"src\\main.rs","byte_start":2282,"byte_end":2286,"line_start":47,"line_end":47,"column_start":4,"column_end":8},"name":"main","qualname":"::main","value":"fn main()","parent":null,"children":[],"decl_id":null,"docs":"","sig":null,"attributes":[{"value":"allow(dead_code)","span":{"file_name":"src\\main.rs","byte_start":0,"byte_end":0,"line_start":1,"line_end":1,"column_start":1,"column_end":1}}]},{"kind":"Local","id":{"krate":0,"index":2415919113},"span":{"file_name":"src\\main.rs","byte_start":2299,"byte_end":2304,"line_start":48,"line_end":48,"column_start":9,"column_end":14},"name":"rect1","qualname":"rect1$HirId { owner: DefId(0:9 ~ structures_5_3_syntacsis_method[77eb]::main), local_id: 9 }","value":"Rectangle","parent":null,"children":[],"decl_id":null,"docs":"","sig":null,"attributes":[]},{"kind":"Local","id":{"krate":0,"index":1509949449},"span":{"file_name":"src\\main.rs","byte_start":5006,"byte_end":5011,"line_start":82,"line_end":82,"column_start":9,"column_end":14},"name":"rect1","qualname":"rect1$HirId { owner: DefId(0:9 ~ structures_5_3_syntacsis_method[77eb]::main), local_id: 90 }","value":"Rectangle","parent":null,"children":[],"decl_id":null,"docs":"","sig":null,"attributes":[]},{"kind":"Local","id":{"krate":0,"index":3321888777},"span":{"file_name":"src\\main.rs","byte_start":5081,"byte_end":5086,"line_start":87,"line_end":87,"column_start":9,"column_end":14},"name":"rect2","qualname":"rect2$HirId { owner: DefId(0:9 ~ structures_5_3_syntacsis_method[77eb]::main), local_id: 99 }","value":"Rectangle","parent":null,"children":[],"decl_id":null,"docs":"","sig":null,"attributes":[]},{"kind":"Local","id":{"krate":0,"index":905969673},"span":{"file_name":"src\\main.rs","byte_start":5156,"byte_end":5161,"line_start":92,"line_end":92,"column_start":9,"column_end":14},"name":"rect3","qualname":"rect3$HirId { owner: DefId(0:9 ~ structures_5_3_syntacsis_method[77eb]::main), local_id: 108 }","value":"Rectangle","parent":null,"children":[],"decl_id":null,"docs":"","sig":null,"attributes":[]},{"kind":"Local","id":{"krate":0,"index":3271557129},"span":{"file_name":"src\\main.rs","byte_start":7112,"byte_end":7114,"line_start":113,"line_end":113,"column_start":9,"column_end":11},"name":"sq","qualname":"sq$HirId { owner: DefId(0:9 ~ structures_5_3_syntacsis_method[77eb]::main), local_id: 195 }","value":"Rectangle","parent":null,"children":[],"decl_id":null,"docs":"","sig":null,"attributes":[]}],"impls":[{"id":0,"kind":"Inherent","span":{"file_name":"src\\main.rs","byte_start":998,"byte_end":1007,"line_start":17,"line_end":17,"column_start":6,"column_end":15},"value":"","parent":null,"children":[{"krate":0,"index":4},{"krate":0,"index":5},{"krate":0,"index":6}],"docs":"","sig":null,"attributes":[]},{"id":1,"kind":"Inherent","span":{"file_name":"src\\main.rs","byte_start":2144,"byte_end":2153,"line_start":41,"line_end":41,"column_start":6,"column_end":15},"value":"","parent":null,"children":[{"krate":0,"index":8}],"docs":"","sig":null,"attributes":[]}],"refs":[{"kind":"Variable","span":{"file_name":"src\\main.rs","byte_start":961,"byte_end":966,"line_start":13,"line_end":13,"column_start":5,"column_end":10},"ref_id":{"krate":0,"index":11}},{"kind":"Variable","span":{"file_name":"src\\main.rs","byte_start":977,"byte_end":983,"line_start":14,"line_end":14,"column_start":5,"column_end":11},"ref_id":{"krate":0,"index":12}},{"kind":"Type","span":{"file_name":"src\\main.rs","byte_start":998,"byte_end":1007,"line_start":17,"line_end":17,"column_start":6,"column_end":15},"ref_id":{"krate":0,"index":10}},{"kind":"Variable","span":{"file_name":"src\\main.rs","byte_start":1046,"byte_end":1050,"line_start":19,"line_end":19,"column_start":9,"column_end":13},"ref_id":{"krate":0,"index":1073741828}},{"kind":"Variable","span":{"file_name":"src\\main.rs","byte_start":1051,"byte_end":1056,"line_start":19,"line_end":19,"column_start":14,"column_end":19},"ref_id":{"krate":0,"index":11}},{"kind":"Variable","span":{"file_name":"src\\main.rs","byte_start":1059,"byte_end":1063,"line_start":19,"line_end":19,"column_start":22,"column_end":26},"ref_id":{"krate":0,"index":1073741828}},{"kind":"Variable","span":{"file_name":"src\\main.rs","byte_start":1064,"byte_end":1070,"line_start":19,"line_end":19,"column_start":27,"column_end":33},"ref_id":{"krate":0,"index":12}},{"kind":"Variable","span":{"file_name":"src\\main.rs","byte_start":1116,"byte_end":1120,"line_start":23,"line_end":23,"column_start":9,"column_end":13},"ref_id":{"krate":0,"index":1073741829}},{"kind":"Variable","span":{"file_name":"src\\main.rs","byte_start":1121,"byte_end":1126,"line_start":23,"line_end":23,"column_start":14,"column_end":19},"ref_id":{"krate":0,"index":11}},{"kind":"Type","span":{"file_name":"src\\main.rs","byte_start":2062,"byte_end":2066,"line_start":34,"line_end":34,"column_start":9,"column_end":13},"ref_id":{"krate":0,"index":10}},{"kind":"Variable","span":{"file_name":"src\\main.rs","byte_start":2081,"byte_end":2086,"line_start":35,"line_end":35,"column_start":13,"column_end":18},"ref_id":{"krate":0,"index":11}},{"kind":"Variable","span":{"file_name":"src\\main.rs","byte_start":2088,"byte_end":2092,"line_start":35,"line_end":35,"column_start":20,"column_end":24},"ref_id":{"krate":0,"index":1073741830}},{"kind":"Variable","span":{"file_name":"src\\main.rs","byte_start":2106,"byte_end":2112,"line_start":36,"line_end":36,"column_start":13,"column_end":19},"ref_id":{"krate":0,"index":12}},{"kind":"Variable","span":{"file_name":"src\\main.rs","byte_start":2114,"byte_end":2118,"line_start":36,"line_end":36,"column_start":21,"column_end":25},"ref_id":{"krate":0,"index":1073741830}},{"kind":"Type","span":{"file_name":"src\\main.rs","byte_start":2144,"byte_end":2153,"line_start":41,"line_end":41,"column_start":6,"column_end":15},"ref_id":{"krate":0,"index":10}},{"kind":"Type","span":{"file_name":"src\\main.rs","byte_start":2186,"byte_end":2195,"line_start":42,"line_end":42,"column_start":32,"column_end":41},"ref_id":{"krate":0,"index":10}},{"kind":"Variable","span":{"file_name":"src\\main.rs","byte_start":2215,"byte_end":2219,"line_start":43,"line_end":43,"column_start":9,"column_end":13},"ref_id":{"krate":0,"index":1073741832}},{"kind":"Variable","span":{"file_name":"src\\main.rs","byte_start":2220,"byte_end":2225,"line_start":43,"line_end":43,"column_start":14,"column_end":19},"ref_id":{"krate":0,"index":11}},{"kind":"Variable","span":{"file_name":"src\\main.rs","byte_start":2228,"byte_end":2233,"line_start":43,"line_end":43,"column_start":22,"column_end":27},"ref_id":{"krate":0,"index":536870920}},{"kind":"Variable","span":{"file_name":"src\\main.rs","byte_start":2234,"byte_end":2239,"line_start":43,"line_end":43,"column_start":28,"column_end":33},"ref_id":{"krate":0,"index":11}},{"kind":"Variable","span":{"file_name":"src\\main.rs","byte_start":2243,"byte_end":2247,"line_start":43,"line_end":43,"column_start":37,"column_end":41},"ref_id":{"krate":0,"index":1073741832}},{"kind":"Variable","span":{"file_name":"src\\main.rs","byte_start":2248,"byte_end":2254,"line_start":43,"line_end":43,"column_start":42,"column_end":48},"ref_id":{"krate":0,"index":12}},{"kind":"Variable","span":{"file_name":"src\\main.rs","byte_start":2257,"byte_end":2262,"line_start":43,"line_end":43,"column_start":51,"column_end":56},"ref_id":{"krate":0,"index":536870920}},{"kind":"Variable","span":{"file_name":"src\\main.rs","byte_start":2263,"byte_end":2269,"line_start":43,"line_end":43,"column_start":57,"column_end":63},"ref_id":{"krate":0,"index":12}},{"kind":"Type","span":{"file_name":"src\\main.rs","byte_start":2307,"byte_end":2316,"line_start":48,"line_end":48,"column_start":17,"column_end":26},"ref_id":{"krate":0,"index":10}},{"kind":"Variable","span":{"file_name":"src\\main.rs","byte_start":2327,"byte_end":2332,"line_start":49,"line_end":49,"column_start":9,"column_end":14},"ref_id":{"krate":0,"index":11}},{"kind":"Variable","span":{"file_name":"src\\main.rs","byte_start":2346,"byte_end":2352,"line_start":50,"line_end":50,"column_start":9,"column_end":15},"ref_id":{"krate":0,"index":12}},{"kind":"Function","span":{"file_name":"src\\main.rs","byte_start":2390,"byte_end":2395,"line_start":52,"line_end":52,"column_start":26,"column_end":31},"ref_id":{"krate":0,"index":5}},{"kind":"Variable","span":{"file_name":"src\\main.rs","byte_start":2384,"byte_end":2389,"line_start":52,"line_end":52,"column_start":20,"column_end":25},"ref_id":{"krate":0,"index":2415919113}},{"kind":"Function","span":{"file_name":"src\\main.rs","byte_start":2468,"byte_end":2472,"line_start":53,"line_end":53,"column_start":69,"column_end":73},"ref_id":{"krate":0,"index":4}},{"kind":"Variable","span":{"file_name":"src\\main.rs","byte_start":2462,"byte_end":2467,"line_start":53,"line_end":53,"column_start":63,"column_end":68},"ref_id":{"krate":0,"index":2415919113}},{"kind":"Type","span":{"file_name":"src\\main.rs","byte_start":5014,"byte_end":5023,"line_start":82,"line_end":82,"column_start":17,"column_end":26},"ref_id":{"krate":0,"index":10}},{"kind":"Variable","span":{"file_name":"src\\main.rs","byte_start":5034,"byte_end":5039,"line_start":83,"line_end":83,"column_start":9,"column_end":14},"ref_id":{"krate":0,"index":11}},{"kind":"Variable","span":{"file_name":"src\\main.rs","byte_start":5053,"byte_end":5059,"line_start":84,"line_end":84,"column_start":9,"column_end":15},"ref_id":{"krate":0,"index":12}},{"kind":"Type","span":{"file_name":"src\\main.rs","byte_start":5089,"byte_end":5098,"line_start":87,"line_end":87,"column_start":17,"column_end":26},"ref_id":{"krate":0,"index":10}},{"kind":"Variable","span":{"file_name":"src\\main.rs","byte_start":5109,"byte_end":5114,"line_start":88,"line_end":88,"column_start":9,"column_end":14},"ref_id":{"krate":0,"index":11}},{"kind":"Variable","span":{"file_name":"src\\main.rs","byte_start":5128,"byte_end":5134,"line_start":89,"line_end":89,"column_start":9,"column_end":15},"ref_id":{"krate":0,"index":12}},{"kind":"Type","span":{"file_name":"src\\main.rs","byte_start":5164,"byte_end":5173,"line_start":92,"line_end":92,"column_start":17,"column_end":26},"ref_id":{"krate":0,"index":10}},{"kind":"Variable","span":{"file_name":"src\\main.rs","byte_start":5184,"byte_end":5189,"line_start":93,"line_end":93,"column_start":9,"column_end":14},"ref_id":{"krate":0,"index":11}},{"kind":"Variable","span":{"file_name":"src\\main.rs","byte_start":5203,"byte_end":5209,"line_start":94,"line_end":94,"column_start":9,"column_end":15},"ref_id":{"krate":0,"index":12}},{"kind":"Function","span":{"file_name":"src\\main.rs","byte_start":5270,"byte_end":5278,"line_start":97,"line_end":97,"column_start":48,"column_end":56},"ref_id":{"krate":0,"index":8}},{"kind":"Variable","span":{"file_name":"src\\main.rs","byte_start":5264,"byte_end":5269,"line_start":97,"line_end":97,"column_start":42,"column_end":47},"ref_id":{"krate":0,"index":1509949449}},{"kind":"Variable","span":{"file_name":"src\\main.rs","byte_start":5280,"byte_end":5285,"line_start":97,"line_end":97,"column_start":58,"column_end":63},"ref_id":{"krate":0,"index":3321888777}},{"kind":"Function","span":{"file_name":"src\\main.rs","byte_start":5336,"byte_end":5344,"line_start":98,"line_end":98,"column_start":48,"column_end":56},"ref_id":{"krate":0,"index":8}},{"kind":"Variable","span":{"file_name":"src\\main.rs","byte_start":5330,"byte_end":5335,"line_start":98,"line_end":98,"column_start":42,"column_end":47},"ref_id":{"krate":0,"index":1509949449}},{"kind":"Variable","span":{"file_name":"src\\main.rs","byte_start":5346,"byte_end":5351,"line_start":98,"line_end":98,"column_start":58,"column_end":63},"ref_id":{"krate":0,"index":905969673}},{"kind":"Function","span":{"file_name":"src\\main.rs","byte_start":7128,"byte_end":7134,"line_start":113,"line_end":113,"column_start":25,"column_end":31},"ref_id":{"krate":0,"index":6}},{"kind":"Type","span":{"file_name":"src\\main.rs","byte_start":7117,"byte_end":7126,"line_start":113,"line_end":113,"column_start":14,"column_end":23},"ref_id":{"krate":0,"index":10}},{"kind":"Variable","span":{"file_name":"src\\main.rs","byte_start":7170,"byte_end":7172,"line_start":114,"line_end":114,"column_start":32,"column_end":34},"ref_id":{"krate":0,"index":3271557129}},{"kind":"Mod","span":{"file_name":"/rustc/e092d0b6b43f2de967af0887873151bb1c0b18d3\\library\\std\\src\\macros.rs","byte_start":35232,"byte_end":35265,"line_start":106,"line_end":106,"column_start":28,"column_end":61},"ref_id":{"krate":2,"index":9537}},{"kind":"Mod","span":{"file_name":"/rustc/e092d0b6b43f2de967af0887873151bb1c0b18d3\\library\\std\\src\\macros.rs","byte_start":35232,"byte_end":35265,"line_start":106,"line_end":106,"column_start":28,"column_end":61},"ref_id":{"krate":2,"index":9854}},{"kind":"Mod","span":{"file_name":"/rustc/e092d0b6b43f2de967af0887873151bb1c0b18d3\\library\\std\\src\\macros.rs","byte_start":35232,"byte_end":35265,"line_start":106,"line_end":106,"column_start":28,"column_end":61},"ref_id":{"krate":2,"index":9855}},{"kind":"Mod","span":{"file_name":"/rustc/e092d0b6b43f2de967af0887873151bb1c0b18d3\\library\\std\\src\\macros.rs","byte_start":35232,"byte_end":35265,"line_start":106,"line_end":106,"column_start":28,"column_end":61},"ref_id":{"krate":2,"index":9537}},{"kind":"Mod","span":{"file_name":"/rustc/e092d0b6b43f2de967af0887873151bb1c0b18d3\\library\\std\\src\\macros.rs","byte_start":35232,"byte_end":35265,"line_start":106,"line_end":106,"column_start":28,"column_end":61},"ref_id":{"krate":2,"index":9854}},{"kind":"Mod","span":{"file_name":"/rustc/e092d0b6b43f2de967af0887873151bb1c0b18d3\\library\\std\\src\\macros.rs","byte_start":35232,"byte_end":35265,"line_start":106,"line_end":106,"column_start":28,"column_end":61},"ref_id":{"krate":2,"index":9855}}],"macro_refs":[],"relations":[{"span":{"file_name":"src\\main.rs","byte_start":998,"byte_end":1007,"line_start":17,"line_end":17,"column_start":6,"column_end":15},"kind":{"Impl":{"id":0}},"from":{"krate":0,"index":10},"to":{"krate":4294967295,"index":4294967295}},{"span":{"file_name":"src\\main.rs","byte_start":2144,"byte_end":2153,"line_start":41,"line_end":41,"column_start":6,"column_end":15},"kind":{"Impl":{"id":1}},"from":{"krate":0,"index":10},"to":{"krate":4294967295,"index":4294967295}}]}